hwpyp/__init__.py
hwpyp/mypy.py
helloworld_pyp-0.0.7.dist-info/LICENSE
helloworld_pyp-0.0.7.dist-info/METADATA
helloworld_pyp-0.0.7.dist-info/WHEEL
helloworld_pyp-0.0.7.dist-info/entry_points.txt
helloworld_pyp-0.0.7.dist-info/top_level.txt
helloworld_pyp-0.0.7.dist-info/RECORD
