Metadata-Version: 2.1
Name: helloworld-pyp
Version: 0.0.7
Summary: My first Python Package
Home-page: https://github.com/mahesh-maximus/helloworld-pyp
Author: Mahesh Maximus
Author-email: 
Project-URL: Bug Tracker, https://github.com/mahesh-maximus/helloworld-pyp/issues
Classifier: Programming Language :: Python :: 3
Classifier: License :: OSI Approved :: MIT License
Requires-Python: >=3.6
License-File: LICENSE
